impactEffects/__init__.py
impactEffects/core/__init__.py
impactEffects/core/config.py
impactEffects/core/core_collins.py
impactEffects/functions/ __init__.py
impactEffects/functions/function.py
impactEffects/instances/ImpactorClass.py
impactEffects/instances/Impactor_population.py
impactEffects/instances/TargetClass.py
impactEffects/instances/__init__.py
impactEffects/utils/__init__.py
impactEffects/utils/impact.py
impactEffects/utils/print.py
ImpactEffect-0.0.3.dist-info/LICENSE
ImpactEffect-0.0.3.dist-info/METADATA
ImpactEffect-0.0.3.dist-info/WHEEL
ImpactEffect-0.0.3.dist-info/top_level.txt
ImpactEffect-0.0.3.dist-info/RECORD
