Metadata-Version: 2.1
Name: ImpactEffect
Version: 0.0.3
Summary: A small example package
Home-page: https://github.com/acse-dx121/impact-effects.git
Author: Imperial College London
Author-email: CarryMeRookie <dx121@ic.ac.uk>
License: MIT License        
Project-URL: Bug Tracker, https://github.com/pypa/sampleproject/issues
Project-URL: Homepage, https://github.com/pypa/sampleproject
Classifier: Programming Language :: Python :: 3
Classifier: License :: OSI Approved :: MIT License
Classifier: Operating System :: OS Independent
Requires-Python: >=3.7
License-File: LICENSE
